covid_shared/__about__.py
covid_shared/__init__.py
covid_shared/ihme_deps.py
covid_shared/parallel.py
covid_shared/paths.py
covid_shared/shell_tools.py
covid_shared/cli_tools/__init__.py
covid_shared/cli_tools/cleanup.py
covid_shared/cli_tools/decorators.py
covid_shared/cli_tools/logging.py
covid_shared/cli_tools/metadata.py
covid_shared/cli_tools/run_directory.py
covid_shared/cli_tools/validation.py
covid_shared/workflow/__init__.py
covid_shared/workflow/specification.py
covid_shared/workflow/template.py
covid_shared/workflow/utilities.py
covid_shared-2.2.1.dist-info/AUTHORS.rst
covid_shared-2.2.1.dist-info/LICENSE
covid_shared-2.2.1.dist-info/METADATA
covid_shared-2.2.1.dist-info/WHEEL
covid_shared-2.2.1.dist-info/top_level.txt
covid_shared-2.2.1.dist-info/RECORD
