Metadata-Version: 2.1
Name: covid-shared
Version: 2.2.1
Summary: Shared utilities for the covid model pipeline.
Home-page: https://github.com/ihmeuw/covid-shared
Author: James Collins
Author-email: collijk@uw.edu
License: UNKNOWN
Platform: UNKNOWN
License-File: LICENSE
License-File: AUTHORS.rst
Requires-Dist: click
Requires-Dist: loguru
Requires-Dist: pandas
Requires-Dist: pathos
Requires-Dist: pyyaml
Requires-Dist: tqdm
Provides-Extra: dev
Requires-Dist: pytest ; extra == 'dev'
Requires-Dist: pytest-mock ; extra == 'dev'
Requires-Dist: sphinx ; extra == 'dev'
Requires-Dist: jobmon[ihme] (==3.0.5) ; extra == 'dev'
Requires-Dist: db-queries (<26,>=25.2.0) ; extra == 'dev'
Provides-Extra: docs
Requires-Dist: sphinx ; extra == 'docs'
Provides-Extra: internal
Requires-Dist: jobmon[ihme] (==3.0.5) ; extra == 'internal'
Requires-Dist: db-queries (<26,>=25.2.0) ; extra == 'internal'
Provides-Extra: test
Requires-Dist: pytest ; extra == 'test'
Requires-Dist: pytest-mock ; extra == 'test'
